pstest/__init__.py
pstest/constant.py
pstest/context.py
pstest/unittest.py
pstest-0.1.5.dist-info/LICENSE
pstest-0.1.5.dist-info/METADATA
pstest-0.1.5.dist-info/WHEEL
pstest-0.1.5.dist-info/top_level.txt
pstest-0.1.5.dist-info/RECORD
