Metadata-Version: 2.1
Name: pstest
Version: 0.1.5
Summary: Python unittest tools for Problem Solving
Maintainer-email: HeoHeo <h0h6h2h5@gmail.com>
License: MIT License
Project-URL: repository, https://github.com/heoh/pstest
Keywords: unittest,test,testing,ps,problem,solving,judge
Classifier: Development Status :: 3 - Alpha
Classifier: Intended Audience :: Developers
Classifier: License :: OSI Approved :: MIT License
Classifier: Operating System :: MacOS
Classifier: Operating System :: Microsoft :: Windows
Classifier: Operating System :: POSIX
Classifier: Operating System :: Unix
Classifier: Programming Language :: Python :: 3 :: Only
Classifier: Programming Language :: Python :: 3.9
Classifier: Programming Language :: Python :: 3.10
Classifier: Programming Language :: Python :: 3.11
Classifier: Programming Language :: Python :: 3.12
Classifier: Programming Language :: Python :: 3.13
Classifier: Topic :: Software Development :: Libraries
Classifier: Topic :: Software Development :: Testing
Classifier: Topic :: Utilities
Requires-Python: >=3.9
License-File: LICENSE
